{
  "comment": "サンプル親　メンテナンス　照会処理",
  "html": "Myapp00/Json/Apps/T_Sample_ParentMainte",
  "dbname": "myapp00",
  "mode": "select",
  "prog": "no",
  "message": {
    "status": "OK",
    "msg": "照会処理は正常に終了しました。"
  },
  "sqls": [{
    "comment": "Ｔサンプル_ヘッダ　照会処理",
    "id": "header",
    "before": "",
    "after": "",
    "sql": {
      "type": "select",
      "freesql": "",
      "genesql": {
        "dist": "",
        "from": 
        [
          "Ｔサンプル_ヘッダ          AS A"
         ,"LEFT OUTER JOIN Ｔサンプル_マスタ AS B ON (A.ref_サンプル_マスタＩＤ = B.サンプル_マスタＩＤ)"
        ],
        "where": "A.サンプル_ヘッダＩＤ = ?",
        "order": ""
      }
    },
    "input": {
      "multiline": "no",
      "record": {
        "サンプル_ヘッダＩＤ": {
          "value": [""]
        }
      }
    },
    "output": {
      "multiline": "no",
      "record": {
        "サンプル_ヘッダＩＤ": {
          "value": [""],
          "table": "A"
        },
        "サンプル_ヘッダ項目０１": {
          "value": [""],
          "table": "A"
        },
        "サンプル_ヘッダ項目０２": {
          "value": [""],
          "table": "A"
        },
        "サンプル_ヘッダ項目０３": {
          "value": [""],
          "table": "A"
        },
        "サンプル_ヘッダ項目０４": {
          "value": [""],
          "table": "A"
        },
        "サンプル_ヘッダ項目０５": {
          "value": [""],
          "table": "A"
        },
        "サンプル_ヘッダ項目０６": {
          "value": [""],
          "table": "A"
        },
        "サンプル_ヘッダ項目０７": {
          "value": [""],
          "table": "A"
        },
        "サンプル_ヘッダ項目０８": {
          "value": [""],
          "table": "A"
        },
        "サンプル_ヘッダ項目０９": {
          "value": [""],
          "table": "A"
        },
        "サンプル_ヘッダ項目１０": {
          "value": [""],
          "table": "A"
        },
        "サンプル_ヘッダ項目１１": {
          "value": [""],
          "table": "A"
        },
        "サンプル_ヘッダ項目１２": {
          "value": [""],
          "table": "A"
        },
        "サンプル_ヘッダ項目１３": {
          "value": [""],
          "table": "A"
        },
        "サンプル_ヘッダ項目１４": {
          "value": [""],
          "table": "A"
        },
        "サンプル_ヘッダ項目１５": {
          "value": [""],
          "table": "A"
        },
        "サンプル_ヘッダ項目１６": {
          "value": [""],
          "table": "A"
        },
        "サンプル_ヘッダ項目１７": {
          "value": [""],
          "table": "A"
        },
        "サンプル_ヘッダ項目１８": {
          "value": [""],
          "table": "A"
        },
        "サンプル_ヘッダ項目１９": {
          "value": [""],
          "table": "A"
        },
        "サンプル_ヘッダ項目２０": {
          "value": [""],
          "table": "A"
        },
        "サンプル_ヘッダ項目２１": {
          "value": [""],
          "table": "A"
        },
        "サンプル_ヘッダ項目２２": {
          "value": [""],
          "table": "A"
        },
        "サンプル_ヘッダ項目２３": {
          "value": [""],
          "table": "A"
        },
        "サンプル_ヘッダ項目２４": {
          "value": [""],
          "table": "A"
        },
        "サンプル_ヘッダ項目２５": {
          "value": [""],
          "table": "A"
        },
        "サンプル_ヘッダ項目２６": {
          "value": [""],
          "table": "A"
        },
        "サンプル_ヘッダ項目２７": {
          "value": [""],
          "table": "A"
        },
        "サンプル_ヘッダ項目２８": {
          "value": [""],
          "table": "A"
        },
        "サンプル_ヘッダ項目２９": {
          "value": [""],
          "table": "A"
        },
        "サンプル_ヘッダ項目３０": {
          "value": [""],
          "table": "A"
        },
        "サンプル_マスタＩＤ": {
          "value": [""],
          "table": "B"
        },
        "サンプル_マスタ項目０１": {
          "value": [""],
          "table": "B"
        }
      }
    }
  }]
}