{
  "comment": "サンプル親　メンテナンス　訂正処理",
  "html": "Myapp00/Json/Apps/T_Sample_ParentMainte",
  "dbname": "myapp00",
  "mode": "update",
  "prog": "yes",
  "message": {
    "status": "OK",
    "msg": "訂正処理は正常に終了しました。"
  },
  "sqls": [{
    "comment": "Ｔサンプル_ヘッダ　訂正処理",
    "id": "header_update",
    "before": "",
    "after": "",
    "sql": {
      "type": "update",
      "freesql": "",
      "genesql": {
        "dist": "",
        "from": "Ｔサンプル_ヘッダ",
        "where": "サンプル_ヘッダＩＤ = ?",
        "order": ""
      }
    },
    "input": {
      "multiline": "no",
      "record": {
        "サンプル_ヘッダ項目０１": {
          "value": [""],
          "fromtype" : "request",
          "fromid" : "header",
          "fromio" : "",
          "fromname" : "サンプル_ヘッダ項目０１"
        },
        "サンプル_ヘッダ項目０２": {
          "value": [""],
          "fromtype" : "request",
          "fromid" : "header",
          "fromio" : "",
          "fromname" : "サンプル_ヘッダ項目０２"
        },
        "サンプル_ヘッダ項目０３": {
          "value": [""],
          "fromtype" : "request",
          "fromid" : "header",
          "fromio" : "",
          "fromname" : "サンプル_ヘッダ項目０３"
        },
        "サンプル_ヘッダ項目０４": {
          "value": [""],
          "fromtype" : "request",
          "fromid" : "header",
          "fromio" : "",
          "fromname" : "サンプル_ヘッダ項目０４"
        },
        "サンプル_ヘッダ項目０５": {
          "value": [""],
          "fromtype" : "request",
          "fromid" : "header",
          "fromio" : "",
          "fromname" : "サンプル_ヘッダ項目０５"
        },
        "サンプル_ヘッダ項目０６": {
          "value": [""],
          "fromtype" : "request",
          "fromid" : "header",
          "fromio" : "",
          "fromname" : "サンプル_ヘッダ項目０６"
        },
        "サンプル_ヘッダ項目０７": {
          "value": [""],
          "fromtype" : "request",
          "fromid" : "header",
          "fromio" : "",
          "fromname" : "サンプル_ヘッダ項目０７"
        },
        "サンプル_ヘッダ項目０８": {
          "value": [""],
          "fromtype" : "request",
          "fromid" : "header",
          "fromio" : "",
          "fromname" : "サンプル_ヘッダ項目０８"
        },
        "サンプル_ヘッダ項目０９": {
          "value": [""],
          "fromtype" : "request",
          "fromid" : "header",
          "fromio" : "",
          "fromname" : "サンプル_ヘッダ項目０９"
        },
        "サンプル_ヘッダ項目１０": {
          "value": [""],
          "fromtype" : "request",
          "fromid" : "header",
          "fromio" : "",
          "fromname" : "サンプル_ヘッダ項目１０"
        },
        "サンプル_ヘッダ項目１１": {
          "value": [""],
          "fromtype" : "request",
          "fromid" : "header",
          "fromio" : "",
          "fromname" : "サンプル_ヘッダ項目１１"
        },
        "サンプル_ヘッダ項目１２": {
          "value": [""],
          "fromtype" : "request",
          "fromid" : "header",
          "fromio" : "",
          "fromname" : "サンプル_ヘッダ項目１２"
        },
        "サンプル_ヘッダ項目１３": {
          "value": [""],
          "fromtype" : "request",
          "fromid" : "header",
          "fromio" : "",
          "fromname" : "サンプル_ヘッダ項目１３"
        },
        "サンプル_ヘッダ項目１４": {
          "value": [""],
          "fromtype" : "request",
          "fromid" : "header",
          "fromio" : "",
          "fromname" : "サンプル_ヘッダ項目１４"
        },
        "サンプル_ヘッダ項目１５": {
          "value": [""],
          "fromtype" : "request",
          "fromid" : "header",
          "fromio" : "",
          "fromname" : "サンプル_ヘッダ項目１５"
        },
        "サンプル_ヘッダ項目１６": {
          "value": [""],
          "fromtype" : "request",
          "fromid" : "header",
          "fromio" : "",
          "fromname" : "サンプル_ヘッダ項目１６"
        },
        "サンプル_ヘッダ項目１７": {
          "value": [""],
          "fromtype" : "request",
          "fromid" : "header",
          "fromio" : "",
          "fromname" : "サンプル_ヘッダ項目１７"
        },
        "サンプル_ヘッダ項目１８": {
          "value": [""],
          "fromtype" : "request",
          "fromid" : "header",
          "fromio" : "",
          "fromname" : "サンプル_ヘッダ項目１８"
        },
        "サンプル_ヘッダ項目１９": {
          "value": [""],
          "fromtype" : "request",
          "fromid" : "header",
          "fromio" : "",
          "fromname" : "サンプル_ヘッダ項目１９"
        },
        "サンプル_ヘッダ項目２０": {
          "value": [""],
          "fromtype" : "request",
          "fromid" : "header",
          "fromio" : "",
          "fromname" : "サンプル_ヘッダ項目２０"
        },
        "サンプル_ヘッダ項目２１": {
          "value": [""],
          "fromtype" : "request",
          "fromid" : "header",
          "fromio" : "",
          "fromname" : "サンプル_ヘッダ項目２１"
        },
        "サンプル_ヘッダ項目２２": {
          "value": [""],
          "fromtype" : "request",
          "fromid" : "header",
          "fromio" : "",
          "fromname" : "サンプル_ヘッダ項目２２"
        },
        "サンプル_ヘッダ項目２３": {
          "value": [""],
          "fromtype" : "request",
          "fromid" : "header",
          "fromio" : "",
          "fromname" : "サンプル_ヘッダ項目２３"
        },
        "サンプル_ヘッダ項目２４": {
          "value": [""],
          "fromtype" : "request",
          "fromid" : "header",
          "fromio" : "",
          "fromname" : "サンプル_ヘッダ項目２４"
        },
        "サンプル_ヘッダ項目２５": {
          "value": [""],
          "fromtype" : "request",
          "fromid" : "header",
          "fromio" : "",
          "fromname" : "サンプル_ヘッダ項目２５"
        },
        "サンプル_ヘッダ項目２６": {
          "value": [""],
          "fromtype" : "request",
          "fromid" : "header",
          "fromio" : "",
          "fromname" : "サンプル_ヘッダ項目２６"
        },
        "サンプル_ヘッダ項目２７": {
          "value": [""],
          "fromtype" : "request",
          "fromid" : "header",
          "fromio" : "",
          "fromname" : "サンプル_ヘッダ項目２７"
        },
        "サンプル_ヘッダ項目２８": {
          "value": [""],
          "fromtype" : "request",
          "fromid" : "header",
          "fromio" : "",
          "fromname" : "サンプル_ヘッダ項目２８"
        },
        "サンプル_ヘッダ項目２９": {
          "value": [""],
          "fromtype" : "request",
          "fromid" : "header",
          "fromio" : "",
          "fromname" : "サンプル_ヘッダ項目２９"
        },
        "サンプル_ヘッダ項目３０": {
          "value": [""],
          "fromtype" : "request",
          "fromid" : "header",
          "fromio" : "",
          "fromname" : "サンプル_ヘッダ項目３０"
        },
        "サンプル_マスタＩＤ": {
          "value": [""],
          "field": "ref_サンプル_マスタＩＤ",
          "fromtype" : "request",
          "fromid" : "header",
          "fromio" : "",
          "fromname" : "サンプル_マスタＩＤ"
        },
        "更新日時": {
          "value": [""],
          "funct": "CURRENT_TIMESTAMP"
        },
        "更新ユーザ": {
          "value": [""],
          "fromtype": "request",
          "fromid": "login",
          "fromio": "",
          "fromname": "ユーザ名称"
        },
        "サンプル_ヘッダＩＤ": {
          "value": [""],
          "fromtype" : "request",
          "fromid" : "header",
          "fromio" : "",
          "fromname" : "サンプル_ヘッダＩＤ"
        }
      }
    }
  },
  {
    "comment": "Ｔサンプル_ヘッダ　照会処理",
    "id": "header",
    "before": "",
    "after": "",
    "sql": {
      "type": "select",
      "freesql": "",
      "genesql": {
        "dist": "",
        "from": 
        [
          "Ｔサンプル_ヘッダ          AS A"
         ,"LEFT OUTER JOIN Ｔサンプル_マスタ AS B ON (A.ref_サンプル_マスタＩＤ = B.サンプル_マスタＩＤ)"
        ],
        "where": "A.サンプル_ヘッダＩＤ = ?",
        "order": ""
      }
    },
    "input": {
      "multiline": "no",
      "record": {
        "サンプル_ヘッダＩＤ": {
          "value": [""],
          "fromtype" : "request",
          "fromid" : "header",
          "fromio" : "",
          "fromname" : "サンプル_ヘッダＩＤ"
        }
      }
    },
    "output": {
      "multiline": "no",
      "record": {
        "サンプル_ヘッダＩＤ": {
          "value": [""],
          "table": "A"
        },
        "サンプル_ヘッダ項目０１": {
          "value": [""],
          "table": "A"
        },
        "サンプル_ヘッダ項目０２": {
          "value": [""],
          "table": "A"
        },
        "サンプル_ヘッダ項目０３": {
          "value": [""],
          "table": "A"
        },
        "サンプル_ヘッダ項目０４": {
          "value": [""],
          "table": "A"
        },
        "サンプル_ヘッダ項目０５": {
          "value": [""],
          "table": "A"
        },
        "サンプル_ヘッダ項目０６": {
          "value": [""],
          "table": "A"
        },
        "サンプル_ヘッダ項目０７": {
          "value": [""],
          "table": "A"
        },
        "サンプル_ヘッダ項目０８": {
          "value": [""],
          "table": "A"
        },
        "サンプル_ヘッダ項目０９": {
          "value": [""],
          "table": "A"
        },
        "サンプル_ヘッダ項目１０": {
          "value": [""],
          "table": "A"
        },
        "サンプル_ヘッダ項目１１": {
          "value": [""],
          "table": "A"
        },
        "サンプル_ヘッダ項目１２": {
          "value": [""],
          "table": "A"
        },
        "サンプル_ヘッダ項目１３": {
          "value": [""],
          "table": "A"
        },
        "サンプル_ヘッダ項目１４": {
          "value": [""],
          "table": "A"
        },
        "サンプル_ヘッダ項目１５": {
          "value": [""],
          "table": "A"
        },
        "サンプル_ヘッダ項目１６": {
          "value": [""],
          "table": "A"
        },
        "サンプル_ヘッダ項目１７": {
          "value": [""],
          "table": "A"
        },
        "サンプル_ヘッダ項目１８": {
          "value": [""],
          "table": "A"
        },
        "サンプル_ヘッダ項目１９": {
          "value": [""],
          "table": "A"
        },
        "サンプル_ヘッダ項目２０": {
          "value": [""],
          "table": "A"
        },
        "サンプル_ヘッダ項目２１": {
          "value": [""],
          "table": "A"
        },
        "サンプル_ヘッダ項目２２": {
          "value": [""],
          "table": "A"
        },
        "サンプル_ヘッダ項目２３": {
          "value": [""],
          "table": "A"
        },
        "サンプル_ヘッダ項目２４": {
          "value": [""],
          "table": "A"
        },
        "サンプル_ヘッダ項目２５": {
          "value": [""],
          "table": "A"
        },
        "サンプル_ヘッダ項目２６": {
          "value": [""],
          "table": "A"
        },
        "サンプル_ヘッダ項目２７": {
          "value": [""],
          "table": "A"
        },
        "サンプル_ヘッダ項目２８": {
          "value": [""],
          "table": "A"
        },
        "サンプル_ヘッダ項目２９": {
          "value": [""],
          "table": "A"
        },
        "サンプル_ヘッダ項目３０": {
          "value": [""],
          "table": "A"
        },
        "サンプル_マスタＩＤ": {
          "value": [""],
          "table": "B"
        },
        "サンプル_マスタ項目０１": {
          "value": [""],
          "table": "B"
        }
      }
    }
  }]
}